myki/__init__.py
myki/mykioxi.py
mykioxi-1.0.0.dist-info/LICENSE
mykioxi-1.0.0.dist-info/METADATA
mykioxi-1.0.0.dist-info/WHEEL
mykioxi-1.0.0.dist-info/entry_points.txt
mykioxi-1.0.0.dist-info/top_level.txt
mykioxi-1.0.0.dist-info/RECORD
