Metadata-Version: 2.1
Name: mykioxi
Version: 1.0.0
Summary: Command line program for Myki oximeter
Home-page: https://github.com/rgerganov/mykioxi
Author: Radoslav Gerganov
Author-email: rgerganov@gmail.com
License: UNKNOWN
Platform: UNKNOWN
Classifier: Programming Language :: Python :: 3
Classifier: License :: OSI Approved :: MIT License
Classifier: Operating System :: OS Independent
Requires-Dist: bleak (>=0.9.1)
